LICENSE
README.md
setup.py
linkplay_cli/__init__.py
linkplay_cli/cli.py
linkplay_cli/config.py
linkplay_cli/configure.py
linkplay_cli/device.py
linkplay_cli/discovery.py
linkplay_cli/firmware_update.py
linkplay_cli/player_status.py
linkplay_cli/tcp_uart.py
linkplay_cli/upnp.py
linkplay_cli/utils.py
linkplay_cli.egg-info/PKG-INFO
linkplay_cli.egg-info/SOURCES.txt
linkplay_cli.egg-info/dependency_links.txt
linkplay_cli.egg-info/entry_points.txt
linkplay_cli.egg-info/requires.txt
linkplay_cli.egg-info/top_level.txt
linkplay_cli/certs/linkplay_client.pem