Metadata-Version: 2.4
Name: linkplay-cli
Version: 0.1.2
Summary: Control Linkplay devices from the comfort of your shell
Home-page: https://github.com/ramikg/linkplay-cli
Classifier: Programming Language :: Python :: 3
License-File: LICENSE
Requires-Dist: async_upnp_client
Requires-Dist: beautifulsoup4
Requires-Dist: construct>=2.10.70
Requires-Dist: lxml
Requires-Dist: prettytable
Requires-Dist: pycryptodome
Requires-Dist: requests
Requires-Dist: urllib3
Dynamic: classifier
Dynamic: description
Dynamic: description-content-type
Dynamic: home-page
Dynamic: license-file
Dynamic: requires-dist
Dynamic: summary
